{"content":"---\ntitle: \"Math Summary (Visual Basic)\"\nms.date: 07/20/2015\nhelpviewer_keywords: \n  - \"math functions, summary\"\n  - \"mathematical functions\"\n  - \"math functions, Visual Basic\"\n  - \"math functions\"\nms.assetid: 6abf2dd7-92d2-488a-8e2b-819be9b30c3f\n---\n# Math Summary (Visual Basic)\nVisual Basic language keywords and run-time library members are organized by purpose and use.  \n  \n|Action|Language element|  \n|------------|----------------------|  \n|Derive trigonometric functions.|<xref:System.Math.Atan%2A>, <xref:System.Math.Cos%2A>, <xref:System.Math.Sin%2A>, <xref:System.Math.Tan%2A>|  \n|General calculations.|<xref:System.Math.Exp%2A>, <xref:System.Math.Log%2A>, <xref:System.Math.Sqrt%2A>|  \n|Generate random numbers.|<xref:Microsoft.VisualBasic.VBMath.Randomize%2A>, <xref:Microsoft.VisualBasic.VBMath.Rnd%2A>|  \n|Get absolute value.|<xref:System.Math.Abs%2A>|  \n|Get the sign of an expression.|<xref:System.Math.Sign%2A>|  \n|Perform numeric conversions.|<xref:Microsoft.VisualBasic.Conversion.Fix%2A>, <xref:Microsoft.VisualBasic.Conversion.Int%2A>|  \n  \n## See also\n\n- [Derived Math Functions](../../../visual-basic/language-reference/keywords/derived-math-functions.md)\n- [Keywords](../../../visual-basic/language-reference/keywords/index.md)\n- [Visual Basic Runtime Library Members](../../../visual-basic/language-reference/runtime-library-members.md)\n","nodes":[{"pos":[4,246],"embed":true,"restype":"x-metadata","content":"title: \"Math Summary (Visual Basic)\"\nms.date: 07/20/2015\nhelpviewer_keywords: \n  - \"math functions, summary\"\n  - \"mathematical functions\"\n  - \"math functions, Visual Basic\"\n  - \"math functions\"\nms.assetid: 6abf2dd7-92d2-488a-8e2b-819be9b30c3f","nodes":[{"content":"Math Summary (Visual Basic)","nodes":[{"pos":[0,27],"content":"Math Summary (Visual Basic)","nodes":[{"content":"Math Summary (Visual Basic)","pos":[0,27]}]}],"path":["title"],"nosxs":false}],"yml":true},{"pos":[253,280],"content":"Math Summary (Visual Basic)","linkify":"Math Summary (Visual Basic)","nodes":[{"content":"Math Summary (Visual Basic)","pos":[0,27]}]},{"content":"Visual Basic language keywords and run-time library members are organized by purpose and use.","pos":[281,374]},{"content":"Action","pos":[381,387]},{"content":"Language element","pos":[388,404]},{"content":"Derive trigonometric functions.","pos":[449,480]},{"pos":[481,588],"content":"<ph id=\"ph1\">&lt;xref:System.Math.Atan%2A&gt;</ph>, <ph id=\"ph2\">&lt;xref:System.Math.Cos%2A&gt;</ph>, <ph id=\"ph3\">&lt;xref:System.Math.Sin%2A&gt;</ph>, <ph id=\"ph4\">&lt;xref:System.Math.Tan%2A&gt;</ph>","source":"<xref:System.Math.Atan%2A>, <xref:System.Math.Cos%2A>, <xref:System.Math.Sin%2A>, <xref:System.Math.Tan%2A>"},{"content":"General calculations.","pos":[593,614]},{"pos":[615,695],"content":"<ph id=\"ph1\">&lt;xref:System.Math.Exp%2A&gt;</ph>, <ph id=\"ph2\">&lt;xref:System.Math.Log%2A&gt;</ph>, <ph id=\"ph3\">&lt;xref:System.Math.Sqrt%2A&gt;</ph>","source":"<xref:System.Math.Exp%2A>, <xref:System.Math.Log%2A>, <xref:System.Math.Sqrt%2A>"},{"content":"Generate random numbers.","pos":[700,724]},{"pos":[725,817],"content":"<ph id=\"ph1\">&lt;xref:Microsoft.VisualBasic.VBMath.Randomize%2A&gt;</ph>, <ph id=\"ph2\">&lt;xref:Microsoft.VisualBasic.VBMath.Rnd%2A&gt;</ph>","source":"<xref:Microsoft.VisualBasic.VBMath.Randomize%2A>, <xref:Microsoft.VisualBasic.VBMath.Rnd%2A>"},{"content":"Get absolute value.","pos":[822,841]},{"content":"Get the sign of an expression.","pos":[872,902]},{"content":"Perform numeric conversions.","pos":[934,962]},{"pos":[963,1057],"content":"<ph id=\"ph1\">&lt;xref:Microsoft.VisualBasic.Conversion.Fix%2A&gt;</ph>, <ph id=\"ph2\">&lt;xref:Microsoft.VisualBasic.Conversion.Int%2A&gt;</ph>","source":"<xref:Microsoft.VisualBasic.Conversion.Fix%2A>, <xref:Microsoft.VisualBasic.Conversion.Int%2A>"},{"pos":[1067,1075],"content":"See also","linkify":"See also","nodes":[{"content":"See also","pos":[0,8]}]},{"pos":[1079,1180],"content":"<bpt id=\"p1\">[</bpt>Derived Math Functions<ept id=\"p1\">](../../../visual-basic/language-reference/keywords/derived-math-functions.md)</ept>","source":"[Derived Math Functions](../../../visual-basic/language-reference/keywords/derived-math-functions.md)"},{"pos":[1183,1253],"content":"<bpt id=\"p1\">[</bpt>Keywords<ept id=\"p1\">](../../../visual-basic/language-reference/keywords/index.md)</ept>","source":"[Keywords](../../../visual-basic/language-reference/keywords/index.md)"},{"pos":[1256,1363],"content":"<bpt id=\"p1\">[</bpt>Visual Basic Runtime Library Members<ept id=\"p1\">](../../../visual-basic/language-reference/runtime-library-members.md)</ept>","source":"[Visual Basic Runtime Library Members](../../../visual-basic/language-reference/runtime-library-members.md)"}]}