{"content":"---\ntitle: \"Trace Type Summary | Microsoft Docs\"\nms.custom: \"\"\nms.date: \"03/30/2017\"\nms.prod: \".net-framework\"\nms.reviewer: \"\"\nms.suite: \"\"\nms.technology: \n  - \"dotnet-clr\"\nms.tgt_pltfrm: \"\"\nms.topic: \"article\"\nms.assetid: e639410b-d1d1-479c-b78e-a4701d4e4085\ncaps.latest.revision: 6\nauthor: \"Erikre\"\nms.author: \"erikre\"\nmanager: \"erikre\"\n---\n# Trace Type Summary\n[Source Levels](http://go.microsoft.com/fwlink/?LinkID=94943) defines various trace levels: Critical, Error, Warning, Information, and Verbose, as well as provides description of the `ActivityTracing` flag, which toggles the output of trace boundary and activity transfer events.  \n  \n You can also review [TraceEventType](http://go.microsoft.com/fwlink/?LinkId=95169) for the types of traces which can be emitted from <xref:System.Diagnostics>.  \n  \n The following table lists the most important ones.  \n  \n|Trace Type|Description|  \n|----------------|-----------------|  \n|Critical|Fatal error or application crash.|  \n|Error|Recoverable error.|  \n|Warning|Informational message.|  \n|Information|Non-critical problem.|  \n|Verbose|Debugging trace.|  \n|Start|Starting of a logical unit of processing.|  \n|Suspend|Suspension of a logical unit of processing.|  \n|Resume|Resumption of a logical unit of processing.|  \n|Stop|Stopping of a logical unit of processing.|  \n|Transfer|Changing of correlation identity.|  \n  \n An activity is defined as a combination of the trace types above.  \n  \n The following is a regular expression that defines an ideal activity in a local (trace source) scope,  \n  \n `R = Start (Critical | Error | Warning | Information | Verbose | Transfer | (Transfer Suspend Transfer Resume) )* Stop`  \n  \n This means that an activity must satisfy the following conditions.  \n  \n-   It must start and stop respectively by a Start and Stop traces  \n  \n-   It must have a Transfer trace immediately preceding a Suspend or Resume trace  \n  \n-   It must not have any traces between the Suspend and Resume traces if such traces exist  \n  \n-   It can have any and as many of critical/Error/Warning/Information/Verbose/Transfer traces as long as the previous conditions are observed  \n  \n The following is a regular expression that defines an ideal activity in the global scope,  \n  \n```  \nR+   \n```  \n  \n with R being the regular expression for an activity in the local scope. This translates to,  \n  \n```  \n[R+ = Start ( Critical | Error | Warning | Information | Verbose | Transfer | (Transfer Suspend Transfer Resume) )* Stop]+  \n```","nodes":[{"pos":[12,47],"content":"Trace Type Summary | Microsoft Docs","needQuote":false,"needEscape":true,"nodes":[{"content":"Trace Type Summary | Microsoft Docs","pos":[0,35]}]},{"pos":[345,363],"content":"Trace Type Summary","linkify":"Trace Type Summary","nodes":[{"content":"Trace Type Summary","pos":[0,18]}]},{"pos":[364,643],"content":"<bpt id=\"p1\">[</bpt>Source Levels<ept id=\"p1\">](http://go.microsoft.com/fwlink/?LinkID=94943)</ept> defines various trace levels: Critical, Error, Warning, Information, and Verbose, as well as provides description of the <ph id=\"ph1\">`ActivityTracing`</ph> flag, which toggles the output of trace boundary and activity transfer events.","source":"[Source Levels](http://go.microsoft.com/fwlink/?LinkID=94943) defines various trace levels: Critical, Error, Warning, Information, and Verbose, as well as provides description of the `ActivityTracing` flag, which toggles the output of trace boundary and activity transfer events."},{"pos":[650,809],"content":"You can also review <bpt id=\"p1\">[</bpt>TraceEventType<ept id=\"p1\">](http://go.microsoft.com/fwlink/?LinkId=95169)</ept> for the types of traces which can be emitted from <ph id=\"ph1\">&lt;xref:System.Diagnostics&gt;</ph>.","source":"You can also review [TraceEventType](http://go.microsoft.com/fwlink/?LinkId=95169) for the types of traces which can be emitted from <xref:System.Diagnostics>."},{"content":"The following table lists the most important ones.","pos":[816,866]},{"content":"Trace Type","pos":[873,883]},{"content":"Description","pos":[884,895]},{"content":"Critical","pos":[939,947]},{"content":"Fatal error or application crash.","pos":[948,981]},{"content":"Error","pos":[986,991]},{"content":"Recoverable error.","pos":[992,1010]},{"content":"Warning","pos":[1015,1022]},{"content":"Informational message.","pos":[1023,1045]},{"content":"Information","pos":[1050,1061]},{"content":"Non-critical problem.","pos":[1062,1083]},{"content":"Verbose","pos":[1088,1095]},{"content":"Debugging trace.","pos":[1096,1112]},{"content":"Start","pos":[1117,1122]},{"content":"Starting of a logical unit of processing.","pos":[1123,1164]},{"content":"Suspend","pos":[1169,1176]},{"content":"Suspension of a logical unit of processing.","pos":[1177,1220]},{"content":"Resume","pos":[1225,1231]},{"content":"Resumption of a logical unit of processing.","pos":[1232,1275]},{"content":"Stop","pos":[1280,1284]},{"content":"Stopping of a logical unit of processing.","pos":[1285,1326]},{"content":"Transfer","pos":[1331,1339]},{"content":"Changing of correlation identity.","pos":[1340,1373]},{"content":"An activity is defined as a combination of the trace types above.","pos":[1381,1446]},{"content":"The following is a regular expression that defines an ideal activity in a local (trace source) scope,","pos":[1453,1554]},{"content":"This means that an activity must satisfy the following conditions.","pos":[1687,1753]},{"content":"It must start and stop respectively by a Start and Stop traces","pos":[1763,1825]},{"content":"It must have a Transfer trace immediately preceding a Suspend or Resume trace","pos":[1835,1912]},{"content":"It must not have any traces between the Suspend and Resume traces if such traces exist","pos":[1922,2008]},{"content":"It can have any and as many of critical/Error/Warning/Information/Verbose/Transfer traces as long as the previous conditions are observed","pos":[2018,2155]},{"content":"The following is a regular expression that defines an ideal activity in the global scope,","pos":[2162,2251]},{"content":"with R being the regular expression for an activity in the local scope.","pos":[2279,2350]},{"content":"This translates to,","pos":[2351,2370]}]}