{"content":"---\ntitle: \"Property '<propertyname>' is 'WriteOnly'\"\nms.date: 07/20/2015\nf1_keywords: \n  - \"vbc30524\"\n  - \"bc30524\"\nhelpviewer_keywords: \n  - \"BC30524\"\nms.assetid: 82249c64-df77-4890-8292-e4da707eca96\n---\n# Property '\\<propertyname>' is 'WriteOnly'\nYou have tried to retrieve a value from a property that is declared `WriteOnly`.  \n  \n **Error ID:** BC30524  \n  \n## To correct this error  \n  \n-   Remove the `WriteOnly` specifier from the property declaration.  \n  \n## See also\n\n- [WriteOnly](../../visual-basic/language-reference/modifiers/writeonly.md)\n","nodes":[{"pos":[4,201],"embed":true,"restype":"x-metadata","content":"title: \"Property '<propertyname>' is 'WriteOnly'\"\nms.date: 07/20/2015\nf1_keywords: \n  - \"vbc30524\"\n  - \"bc30524\"\nhelpviewer_keywords: \n  - \"BC30524\"\nms.assetid: 82249c64-df77-4890-8292-e4da707eca96","nodes":[{"content":"Property '<propertyname>' is 'WriteOnly'","nodes":[{"pos":[0,40],"content":"Property '<ph id=\"ph1\">&lt;propertyname&gt;</ph>' is 'WriteOnly'","source":"Property '<propertyname>' is 'WriteOnly'"}],"path":["title"],"nosxs":false}],"yml":true},{"pos":[208,249],"content":"Property '\\<propertyname>' is 'WriteOnly'","linkify":"Property '\\<propertyname>' is 'WriteOnly'","nodes":[{"content":"Property '<ph id=\"ph1\">\\&lt;</ph>propertyname&gt;' is 'WriteOnly'","pos":[0,41],"source":"Property '\\<propertyname>' is 'WriteOnly'"}]},{"pos":[250,330],"content":"You have tried to retrieve a value from a property that is declared <ph id=\"ph1\">`WriteOnly`</ph>.","source":"You have tried to retrieve a value from a property that is declared `WriteOnly`."},{"pos":[337,358],"content":"<bpt id=\"p1\">**</bpt>Error ID:<ept id=\"p1\">**</ept> BC30524","source":"**Error ID:** BC30524"},{"pos":[367,388],"content":"To correct this error","linkify":"To correct this error","nodes":[{"content":"To correct this error","pos":[0,21]}]},{"pos":[398,461],"content":"Remove the <ph id=\"ph1\">`WriteOnly`</ph> specifier from the property declaration.","source":"Remove the `WriteOnly` specifier from the property declaration."},{"pos":[470,478],"content":"See also","linkify":"See also","nodes":[{"content":"See also","pos":[0,8]}]},{"pos":[482,555],"content":"<bpt id=\"p1\">[</bpt>WriteOnly<ept id=\"p1\">](../../visual-basic/language-reference/modifiers/writeonly.md)</ept>","source":"[WriteOnly](../../visual-basic/language-reference/modifiers/writeonly.md)"}]}